.DS_Store
plagiat/__init__.py
plagiat/cosine.py
plagiat/deteksi.py
plagiat/jaccard.py
plagiat/rabin_karp.py
plagiat-0.1.6.dist-info/METADATA
plagiat-0.1.6.dist-info/WHEEL
plagiat-0.1.6.dist-info/top_level.txt
plagiat-0.1.6.dist-info/RECORD
