Metadata-Version: 2.1
Name: plagiat
Version: 0.1.6
Summary: Library untuk memeriksa tingkat plagiarisme.
Home-page: https://github.com/novay/python/tree/main/plagiat
Author: Novianto Rahmadi
Author-email: novay@btekno.id
License: MIT
Classifier: Intended Audience :: Developers
Classifier: License :: OSI Approved :: MIT License
Classifier: Programming Language :: Python
Classifier: Programming Language :: Python :: 3
Classifier: Programming Language :: Python :: 3.6
Classifier: Programming Language :: Python :: 3.7
Classifier: Programming Language :: Python :: 3.8
Classifier: Programming Language :: Python :: 3.9
Classifier: Operating System :: OS Independent
Requires-Dist: requests
